[
  {
    "type": "header",
    "title": "日本語パワードリル [N1 文法]"
  },
  {
    "type": "mondai_2",
    "id": "m2-q1",
    "questionText": "慎重な ____ ____ ★ ____ まったく危険を顧(かえり)みない。",
    "options": [
      "きたら",
      "ひきかえ",
      "弟に",
      "兄と"
    ],
    "correctIndex": -1,
    "explanation": ""
  },
  {
    "type": "mondai_2",
    "id": "m2-q2",
    "questionText": "いかに父が ____ ____ ★ ____ 、そんな高い山に一人で登るのは無理だろう。",
    "options": [
      "若者",
      "健康",
      "といえども",
      "じゃあるまいし"
    ],
    "correctIndex": -1,
    "explanation": ""
  },
  {
    "type": "mondai_2",
    "id": "m2-q3",
    "questionText": "山一面に咲く桜はここ ____ ____ ★ ____ が訪れる。",
    "options": [
      "多くの観光客",
      "ならではの",
      "眺め",
      "とあって"
    ],
    "correctIndex": -1,
    "explanation": ""
  },
  {
    "type": "mondai_2",
    "id": "m2-q4",
    "questionText": "お互いに率直に ____ ____ ★ ____ はずがない。",
    "options": [
      "理解しあえる",
      "には",
      "なし",
      "話し合うこと"
    ],
    "correctIndex": -1,
    "explanation": ""
  },
  {
    "type": "mondai_3",
    "passageText": "恋とは楽しいものだろうか、辛く苦しいものだろうか。\nその答えが「どちらも」であるのは[ 1 ]だろう。どんな時代のどんな小説や映画を見ても、恋は、あるときは楽しく、またあるときは、辛く苦しいものだ。\n恋が辛いのはなぜか。Aさんのことが[ 2 ]のに、Aさんが同じように自分を好きになってくれない、それどころか、別の人と付き合っている。このように、自分がどれだけ強い気持ちを持っていても、それが相手に届かないことが、恋を辛くさせている原因だ。\nでは、恋は実れば楽しいだけかというと、そんなことはない。「相手がいつまでも私のことを好きでいてくれるだろうか」「ひょっとしたら、相手は私ほど自分のことを好きじゃないかもしれない」など、恋人に[ 3 ]、やはり悩みはつきないのである。",
    "questions": [
      {
        "id": "m3-q1",
        "questionText": "1",
        "options": [
          "言うほかない",
          "言うまでもない",
          "言わざるを得ない",
          "言わねばならない"
        ],
        "correctIndex": -1,
        "explanation": ""
      },
      {
        "id": "m3-q2",
        "questionText": "2",
        "options": [
          "好きでかなわない",
          "好きとは限らない",
          "好きでたまらない",
          "好きなわけではない"
        ],
        "correctIndex": -1,
        "explanation": ""
      },
      {
        "id": "m3-q3",
        "questionText": "3",
        "options": [
          "なったが最後",
          "なったらなったで",
          "なりもしないうちから",
          "なるにつけならないにつけ"
        ],
        "correctIndex": -1,
        "explanation": ""
      }
    ]
  }
]
